lemniscat/plugin/powershell/__init__.py
lemniscat/plugin/powershell/filestore.py
lemniscat/plugin/powershell/main.py
lemniscat/plugin/powershell/plugin.yaml
lemniscat/plugin/powershell/powershell.py
lemniscat/plugin/powershell/requirements.txt
lemniscat.plugin.powershell-0.2.1.dist-info/LICENSE
lemniscat.plugin.powershell-0.2.1.dist-info/METADATA
lemniscat.plugin.powershell-0.2.1.dist-info/WHEEL
lemniscat.plugin.powershell-0.2.1.dist-info/top_level.txt
lemniscat.plugin.powershell-0.2.1.dist-info/RECORD
