Metadata-Version: 2.1
Name: lemniscat.plugin.powershell
Version: 0.2.1
Summary: A lemniscat plugin to run powershell scripts
Author-email: Philippe MORISSEAU <philippe.morisseau@outlook.com>
License: MIT
Project-URL: Homepage, https://github.com/lemniscat-devops/lemniscat.plugin.powershell
Project-URL: Issues, https://github.com/lemniscat-devops/lemniscat.plugin.powershell/issues
Classifier: Programming Language :: Python :: 3
Classifier: License :: OSI Approved :: MIT License
Classifier: Operating System :: OS Independent
Requires-Python: >=3.10
License-File: LICENSE
Requires-Dist: lemniscat.core >=0.2.0
Requires-Dist: PyYAML ==6.0.1
Requires-Dist: pytz ==2023.3
